registration/admin.py
registration/auth_urls.py
registration/auth_urls_classes.py
registration/auth_urls_functions.py
registration/backends/__init__.py
registration/backends/default/__init__.py
registration/backends/default/urls.py
registration/backends/default/views.py
registration/backends/hmac/__init__.py
registration/backends/hmac/urls.py
registration/backends/hmac/views.py
registration/backends/model_activation/__init__.py
registration/backends/model_activation/urls.py
registration/backends/model_activation/views.py
registration/backends/simple/__init__.py
registration/backends/simple/urls.py
registration/backends/simple/views.py
registration/forms.py
registration/locale/ar/LC_MESSAGES/django.mo
registration/locale/ar/LC_MESSAGES/django.po
registration/locale/bg/LC_MESSAGES/django.mo
registration/locale/bg/LC_MESSAGES/django.po
registration/locale/ca/LC_MESSAGES/django.mo
registration/locale/ca/LC_MESSAGES/django.po
registration/locale/cs/LC_MESSAGES/django.mo
registration/locale/cs/LC_MESSAGES/django.po
registration/locale/da/LC_MESSAGES/django.mo
registration/locale/da/LC_MESSAGES/django.po
registration/locale/de/LC_MESSAGES/django.mo
registration/locale/de/LC_MESSAGES/django.po
registration/locale/el/LC_MESSAGES/django.mo
registration/locale/el/LC_MESSAGES/django.po
registration/locale/en/LC_MESSAGES/django.mo
registration/locale/en/LC_MESSAGES/django.po
registration/locale/es/LC_MESSAGES/django.mo
registration/locale/es/LC_MESSAGES/django.po
registration/locale/es_AR/LC_MESSAGES/django.mo
registration/locale/es_AR/LC_MESSAGES/django.po
registration/locale/fa/LC_MESSAGES/django.mo
registration/locale/fa/LC_MESSAGES/django.po
registration/locale/fr/LC_MESSAGES/django.mo
registration/locale/fr/LC_MESSAGES/django.po
registration/locale/he/LC_MESSAGES/django.mo
registration/locale/he/LC_MESSAGES/django.po
registration/locale/hr/LC_MESSAGES/django.mo
registration/locale/hr/LC_MESSAGES/django.po
registration/locale/is/LC_MESSAGES/django.mo
django3_registration-2.6.0.dist-info/LICENSE
django3_registration-2.6.0.dist-info/WHEEL
django3_registration-2.6.0.dist-info/METADATA
django3_registration-2.6.0.dist-info/RECORD
