Metadata-Version: 2.1
Name: django3-registration
Version: 2.6.0
Summary: An extensible user-registration application for Django
Home-page: https://github.com/ImaginaryLandscape/django3-registration
License: BSD
Author: James Bennett
Author-email: james@b-list.org
Maintainer: Imagescape
Maintainer-email: info@imagescape.com
Requires-Python: >=3.6,<4.0
Classifier: License :: Other/Proprietary License
Classifier: Programming Language :: Python :: 3
Classifier: Programming Language :: Python :: 3.10
Classifier: Programming Language :: Python :: 3.6
Classifier: Programming Language :: Python :: 3.7
Classifier: Programming Language :: Python :: 3.8
Classifier: Programming Language :: Python :: 3.9
Requires-Dist: Django (>=3.1,<4.0)
Requires-Dist: confusable_homoglyphs (>=3.0,<4.0)
